sport80/__init__.py
sport80/helpers.py
sport80/pages_enum.py
sport80/request_dataclasses.py
sport80/sport80.py
sport80/sport80_http_client.py
sport80-2.2.6.dist-info/LICENSE
sport80-2.2.6.dist-info/METADATA
sport80-2.2.6.dist-info/WHEEL
sport80-2.2.6.dist-info/top_level.txt
sport80-2.2.6.dist-info/RECORD
